{
"type": "FeatureCollection",
"name": "CP 255 Final Project San Leandro Schools",
"crs": { "type": "name", "properties": { "name": "urn:ogc:def:crs:OGC:1.3:CRS84" } },
"features": [
{ "type": "Feature", "properties": { "County": "Alameda", "SchoolName": "Garfield Elementary", "City": "San Leandro", "GradeLow": "KG", "GradeHigh": "05", "Latitude": 37.70370496, "Longitude": -122.18541317, "EnrollTotal": 338, "Type": "Public", "index_right": 73, "geoid": 6001432400, "state_fip": "06", "county_fip": "001", "tract": "432400", "tot_pop": 6583, "tot_pop_po": 6414, "tot_pop_ci": 6583, "tot_hh": 1822, "tot_fam": 1295, "tot_pop_ov": 6311, "pop_over75": 263, "pop_poc": 5324, "pop_spfam": 260, "pop_lep": 708, "pop_below2": 1880, "pop_disabi": 616, "pop_hus_re": 207, "pop_zvhhs": 149, "pct_over75": 0.0399513899438, "pct_poc": 0.80874981011699998, "pct_spfam": 0.200772200772, "pct_lep": 0.112185073681, "pct_below2": 0.29310882444699998, "pct_disab": 0.093574358195399998, "pct_hus_re": 0.113611416026, "pct_zvhhs": 0.081778265642200004, "over75_1_2": 0, "poc_1_2": 1, "spfam_1_2": 1, "lep_1_2": 0, "below2_1_2": 1, "disab_1_2": 0, "hus_re_1_2": 0, "zvhh_1_2": 0, "epc_2035": 1, "epc_2040": 1, "epc_2050": 1, "c2040_2050": 0, "epc_class": "High" }, "geometry": { "type": "Point", "coordinates": [ -122.185413172366665, 37.703704955047193 ] } }
]
}
